LICENSE
README.md
setup.cfg
setup.py
django_webpack_dev_server/__init__.py
django_webpack_dev_server/apps.py
django_webpack_dev_server.egg-info/PKG-INFO
django_webpack_dev_server.egg-info/SOURCES.txt
django_webpack_dev_server.egg-info/dependency_links.txt
django_webpack_dev_server.egg-info/requires.txt
django_webpack_dev_server.egg-info/top_level.txt
django_webpack_dev_server/management/__init__.py
django_webpack_dev_server/management/constants.py
django_webpack_dev_server/management/generator.py
django_webpack_dev_server/management/commands/__init__.py
django_webpack_dev_server/management/commands/generate.py
django_webpack_dev_server/management/template_constants/__init__.py
django_webpack_dev_server/management/template_constants/development/__init__.py
django_webpack_dev_server/management/template_constants/development/development_constants.py
django_webpack_dev_server/management/template_constants/development/reactjs_constants.py
django_webpack_dev_server/management/template_constants/development/reactts_constants.py
django_webpack_dev_server/management/template_constants/production/__init__.py
django_webpack_dev_server/management/template_constants/production/production_constants.py
django_webpack_dev_server/management/template_constants/production/reactjs_constants.py
django_webpack_dev_server/management/template_constants/production/reactts_constants.py
django_webpack_dev_server/migrations/__init__.py
mysite/__init__.py
mysite/asgi.py
mysite/settings.py
mysite/urls.py
mysite/wsgi.py
tests/__init__.py
tests/test_settings.py
tests/management/__init__.py
tests/management/test_generator.py
tests/management/commands/__init__.py
tests/management/commands/test_generate.py