Metadata-Version: 2.1
Name: django-webpack-dev-server
Version: 0.0.17
Summary: A Django app to setup configuration files for React in a Django Project.
Home-page: https://github.com/Jitensid/django-webpack-dev-server
Author: Jiten Sidhpura
Author-email: jitensidhpura2000@gmail.com
License: MIT
Download-URL: https://github.com/Jitensid/django-webpack-dev-server/archive/refs/tags/0.0.17.tar.gz
Keywords: django,react,webpack4,webpack_dev_server,command-line,project-generator,template-generator,javascript,typescript
Platform: UNKNOWN
Classifier: Intended Audience :: Developers
Classifier: Topic :: Software Development :: Code Generators
Classifier: Framework :: Django
Classifier: License :: OSI Approved :: MIT License
Classifier: Operating System :: OS Independent
Classifier: Programming Language :: Python :: 3.6
Classifier: Programming Language :: Python :: 3.7
Classifier: Programming Language :: Python :: 3.8
Classifier: Programming Language :: Python :: 3.9
Classifier: Programming Language :: Python :: 3.10
License-File: LICENSE
